[
    {
        "EditorCameraComponent": {
            "firstPersonCtrl": false,
            "isActive": false,
            "mouseLookSpeed": 0.11999999731779099,
            "moveSpeed": 0.5600000023841858,
            "orthoScale": 23.479984283447266,
            "position": [
                -42.63152313232422,
                18.953737258911133,
                16.886119842529297
            ],
            "reposition": true,
            "type": 1,
            "upDirection": [
                0.46415579319000244,
                0.8715921640396118,
                -0.15775486826896667
            ],
            "viewDirection": [
                0.8252311944961548,
                -0.49023178219795227,
                -0.2804752290248871
            ]
        },
        "name": "EditorCamera"
    },
    {
        "MeshComponent": {
            "material": "data/materials/grid-gray.json",
            "model": "data/models/scene1.gltf"
        },
        "PhysicsBodyComponent": {
            "damping": [
                0.699999988079071,
                0.699999988079071
            ],
            "friction": [
                0.5,
                0.5
            ],
            "isSensor": false,
            "mass": 0.0,
            "restitution": 0.5,
            "type": 0
        },
        "PhysicsShapeComponent": {
            "mesh": "data/models/scene1.gltf",
            "meshScale": [
                1.0,
                1.0,
                1.0
            ],
            "position": [
                0.0,
                0.0,
                0.0
            ],
            "rotation": [
                0.0,
                0.0,
                0.0,
                1.0
            ],
            "type": 3
        },
        "TransformComponent": {
            "disableRelRotation": false,
            "rotation": [
                0.0,
                0.0,
                0.0,
                1.0
            ],
            "scale": [
                1.0,
                1.0,
                1.0
            ],
            "translation": [
                0.0,
                0.0,
                0.0
            ]
        },
        "name": "Scene1CompositeMesh"
    },
    {
        "EditorCameraComponent": {
            "firstPersonCtrl": true,
            "isActive": true,
            "mouseLookSpeed": 0.1599999964237213,
            "moveSpeed": 10.0,
            "orthoScale": 48.49983215332031,
            "position": [
                -16.010473251342773,
                6.235566139221191,
                6.100191593170166
            ],
            "reposition": false,
            "type": 0,
            "upDirection": [
                0.331948846578598,
                0.927391767501831,
                0.17249484360218048
            ],
            "viewDirection": [
                0.8229178786277771,
                -0.37409156560897827,
                0.4276233911514282
            ]
        },
        "name": "PerspectiveEditorCamera"
    },
    {
        "LightComponent": {
            "attenuation": 30.0,
            "blurRadius": 2.869999885559082,
            "castShadows": true,
            "color": [
                1.0,
                0.9613609910011292,
                0.6715686321258545
            ],
            "intensity": 19.40003776550293,
            "isEnabled": true,
            "projectionTexture": "resources/textures/spot-clouds.png",
            "radius": 15.69996452331543,
            "shadowBias": 0.004999999888241291,
            "shadowResolution": 2048,
            "type": "DIRECT"
        },
        "TransformComponent": {
            "disableRelRotation": false,
            "rotation": [
                0.9028082489967346,
                -0.05540781468153,
                -0.17812089622020721,
                -0.3874792754650116
            ],
            "scale": [
                1.0,
                1.0000007152557373,
                0.9999998807907104
            ],
            "translation": [
                -10.680068969726563,
                9.38753604888916,
                -1.9205152988433838
            ]
        },
        "name": "SunDirectLight"
    },
    {
        "MeshComponent": {
            "material": "",
            "model": "data/models/shadow-mask.gltf"
        },
        "TransformComponent": {
            "disableRelRotation": false,
            "rotation": [
                0.0,
                0.0,
                0.0,
                1.0
            ],
            "scale": [
                1.0,
                1.0,
                1.0
            ],
            "translation": [
                0.0,
                -0.6545529365539551,
                -0.5227241516113281
            ]
        },
        "name": "ShadowMaskMesh"
    },
    {
        "LightComponent": {
            "attenuation": 11.400196075439453,
            "blurRadius": 1.0,
            "castShadows": true,
            "color": [
                0.8235294222831726,
                0.9273356199264526,
                1.0
            ],
            "intensity": 0.6999999284744263,
            "isEnabled": false,
            "shadowBias": 9.999999747378752e-05,
            "shadowResolution": 512,
            "type": "OMNI"
        },
        "TransformComponent": {
            "disableRelRotation": false,
            "rotation": [
                0.0,
                0.0,
                0.0,
                1.0
            ],
            "scale": [
                1.0,
                1.0,
                1.0
            ],
            "translation": [
                -1.3757010698318481,
                1.0908311605453491,
                -2.4926178455352783
            ]
        },
        "name": "InteriorOmniLight1"
    },
    {
        "LightComponent": {
            "attenuation": 56.39990234375,
            "blurRadius": 20.0,
            "castShadows": true,
            "color": [
                0.24019604921340942,
                0.6871398091316223,
                1.0
            ],
            "intensity": 1.200000286102295,
            "isEnabled": true,
            "shadowBias": 0.0001500000071246177,
            "shadowResolution": 128,
            "type": "OMNI"
        },
        "TransformComponent": {
            "disableRelRotation": false,
            "rotation": [
                0.0,
                0.0,
                0.0,
                1.0
            ],
            "scale": [
                1.0,
                1.0,
                1.0
            ],
            "translation": [
                -10.257477760314941,
                7.709251403808594,
                19.444978713989258
            ]
        },
        "name": "OutdoorOmniLight"
    },
    {
        "SkyComponent": {
            "cubeMap": "resources/textures/sky2/*.png"
        },
        "name": "Sky"
    },
    {
        "CameraComponent": {
            "disableRelRotation": true,
            "isActive": false,
            "position": [
                0.0,
                0.0,
                0.0
            ],
            "upDirection": [
                0.0,
                1.0,
                0.0
            ],
            "viewDirection": [
                0.0,
                0.0,
                1.0
            ]
        },
        "MainCharacterBehaviourComponent": {
            "active": true,
            "cameraAttachment": [
                0.0,
                1.7000000476837158,
                0.0
            ],
            "cameraName": "",
            "lookDirection": [
                0.9892731308937073,
                0.1016245111823082,
                0.10493476688861847
            ],
            "mlookSpeed": 0.15000000596046448,
            "moveSpeed": 10.0
        },
        "MeshComponent": {
            "material": "",
            "model": "data/models/character-capsule.gltf"
        },
        "PhysicsCharacterComponent": {
            "height": 1.75,
            "radius": 0.25
        },
        "TransformComponent": {
            "disableRelRotation": false,
            "rotation": [
                0.0,
                0.0,
                0.0,
                1.0
            ],
            "scale": [
                1.0,
                1.0,
                1.0
            ],
            "translation": [
                -11.319541931152344,
                1.3991258144378662,
                8.923778533935547
            ]
        },
        "name": "CharacterController"
    },
    {
        "LightComponent": {
            "attenuation": 16.80002784729004,
            "blurRadius": 1.0,
            "castShadows": true,
            "color": [
                1.0,
                0.44607841968536377,
                0.44607841968536377
            ],
            "intensity": 5.899998664855957,
            "isEnabled": true,
            "shadowBias": 9.999999747378752e-05,
            "shadowResolution": 512,
            "type": "OMNI"
        },
        "TransformComponent": {
            "disableRelRotation": false,
            "rotation": [
                0.0,
                0.0,
                0.0,
                1.0
            ],
            "scale": [
                1.0,
                1.0,
                1.0
            ],
            "translation": [
                -1.60272216796875,
                3.5718843936920166,
                11.040018081665039
            ]
        },
        "name": "CenterLight"
    },
    {
        "LightComponent": {
            "attenuation": 9.19999885559082,
            "beamAngle": 113.0,
            "blurRadius": 10.25,
            "castShadows": true,
            "color": [
                0.6929066181182861,
                0.6519607901573181,
                1.0
            ],
            "intensity": 10.500003814697266,
            "isEnabled": true,
            "projectionTexture": "resources/textures/spot-proj-4.png",
            "shadowBias": 5.999999848427251e-05,
            "shadowResolution": 512,
            "type": "SPOT"
        },
        "TransformComponent": {
            "disableRelRotation": false,
            "rotation": [
                -0.7071066498756409,
                0.0,
                0.0,
                0.70710688829422
            ],
            "scale": [
                1.0,
                0.9999998211860657,
                0.9999998211860657
            ],
            "translation": [
                -10.17956829071045,
                2.244713068008423,
                18.81990623474121
            ]
        },
        "name": "SpotLight1"
    },
    {
        "LightComponent": {
            "attenuation": 9.19999885559082,
            "beamAngle": 135.5,
            "blurRadius": 10.25,
            "castShadows": true,
            "color": [
                0.6929066181182861,
                0.6519607901573181,
                1.0
            ],
            "intensity": 15.100021362304688,
            "isEnabled": true,
            "projectionTexture": "resources/textures/spot-proj-4.png",
            "shadowBias": 5.999999848427251e-05,
            "shadowResolution": 512,
            "type": "SPOT"
        },
        "TransformComponent": {
            "disableRelRotation": false,
            "rotation": [
                -0.7071066498756409,
                0.0,
                0.0,
                0.70710688829422
            ],
            "scale": [
                1.0,
                0.9999997615814209,
                0.9999997615814209
            ],
            "translation": [
                -1.57035231590271,
                2.2475357055664063,
                24.009462356567383
            ]
        },
        "name": "SpotLight2"
    },
    {
        "LightComponent": {
            "attenuation": 9.19999885559082,
            "beamAngle": 136.5,
            "blurRadius": 10.25,
            "castShadows": true,
            "color": [
                0.6929066181182861,
                0.6519607901573181,
                1.0
            ],
            "intensity": 15.100021362304688,
            "isEnabled": true,
            "projectionTexture": "resources/textures/spot-proj-4.png",
            "shadowBias": 5.999999848427251e-05,
            "shadowResolution": 512,
            "type": "SPOT"
        },
        "TransformComponent": {
            "disableRelRotation": false,
            "rotation": [
                -0.7071066498756409,
                0.0,
                0.0,
                0.70710688829422
            ],
            "scale": [
                1.0,
                0.9999997019767761,
                0.9999997019767761
            ],
            "translation": [
                6.383544445037842,
                2.1242868900299072,
                24.009462356567383
            ]
        },
        "name": "SpotLight3"
    },
    {
        "LightComponent": {
            "attenuation": 4.5999979972839355,
            "blurRadius": 19.489999771118164,
            "castShadows": true,
            "color": [
                1.0,
                0.8044982552528381,
                0.44607841968536377
            ],
            "intensity": 2.500001907348633,
            "isEnabled": true,
            "shadowBias": 0.0002800000074785203,
            "shadowResolution": 256,
            "type": "OMNI"
        },
        "TransformComponent": {
            "disableRelRotation": false,
            "rotation": [
                0.0,
                0.0,
                0.0,
                1.0
            ],
            "scale": [
                1.0,
                1.0,
                1.0
            ],
            "translation": [
                7.129344463348389,
                -0.3636370897293091,
                23.973054885864258
            ]
        },
        "name": "CenterLight-COPY"
    }
]